{
  "homing_offset": [
    0,
    0,
    0,
    0,
    0,
    0
  ],
  "drive_mode": [
    0,
    0,
    0,
    0,
    0,
    0
  ],
  "start_pos": [
    2048,
    2048,
    2047,
    2047,
    2047,
    1231
  ],
  "end_pos": [
    4096,
    4096,
    4095,
    4095,
    4095,
    2469
  ],
  "calib_mode": [
    "DEGREE",
    "DEGREE",
    "DEGREE",
    "DEGREE",
    "DEGREE",
    "LINEAR"
  ],
  "motor_names": [
    "shoulder_pan",
    "shoulder_lift",
    "elbow_flex",
    "wrist_flex",
    "wrist_roll",
    "gripper"
  ],
  "kind": "leader",
  "range_min": [
    751,
    785,
    938,
    820,
    0,
    1231
  ],
  "range_max": [
    3422,
    3146,
    3143,
    3119,
    4095,
    2469
  ]
}
